langdiff/__init__.py
langdiff/py.typed
langdiff/parser/__init__.py
langdiff/parser/decoder.py
langdiff/parser/model.py
langdiff/parser/parser.py
langdiff/tracker/__init__.py
langdiff/tracker/change_tracker.py
langdiff/tracker/changes.py
langdiff/tracker/impl.py
langdiff-0.2.0.dist-info/METADATA
langdiff-0.2.0.dist-info/WHEEL
langdiff-0.2.0.dist-info/licenses/LICENSE
langdiff-0.2.0.dist-info/RECORD
