Metadata-Version: 2.4
Name: langdiff
Version: 0.2.0
Summary: LangDiff is a Python library that solves the hard problems of streaming structured LLM outputs to frontends.
Project-URL: Homepage, https://github.com/globalaiplatform/langdiff
Project-URL: Documentation, https://langdiff.readthedocs.io/en/latest/
Author-email: Global AI Platform <contact@a15t.com>
Maintainer-email: Taeho Kim <thk@a15t.com>
License-Expression: Apache-2.0
License-File: LICENSE
Requires-Python: >=3.11
Requires-Dist: jiter>=0.10.0
Requires-Dist: jsonpatch>=1.33
Requires-Dist: jsonpointer>=3.0.0
Requires-Dist: pydantic<3,>=2
